LICENSE
MANIFEST.in
README.md
VERSION
pyproject.toml
requirements.txt
setup.py
covalent_braket_plugin/__init__.py
covalent_braket_plugin/braket.py
covalent_braket_plugin/scripts.py
covalent_braket_plugin.egg-info/PKG-INFO
covalent_braket_plugin.egg-info/SOURCES.txt
covalent_braket_plugin.egg-info/dependency_links.txt
covalent_braket_plugin.egg-info/entry_points.txt
covalent_braket_plugin.egg-info/requires.txt
covalent_braket_plugin.egg-info/top_level.txt